AUTHORS.txt
CHANGES.txt
LICENSE.txt
MANIFEST.in
README
README.rst
setup.cfg
setup.py
MooseGesture.egg-info/PKG-INFO
MooseGesture.egg-info/SOURCES.txt
MooseGesture.egg-info/dependency_links.txt
MooseGesture.egg-info/top_level.txt
docs/Makefile
docs/conf.py
docs/index.rst
docs/make.bat
moosegesture/__init__.py
tests/demoGestureApp.py
tests/test_moosegesture.py